[{"name":"name","count":7},{"name":"searchValue","count":7},{"name":"onSearchValueChange","count":7},{"name":"selectedCategoryValue","count":7},{"name":"onCategoryChange","count":7},{"name":"categoryOptions","count":7},{"name":"searchInputWidth","count":6},{"name":"equalButtonWidth","count":5},{"name":"categoryOptionsWidth","count":5},{"name":"onSearchInputFocus","count":4},{"name":"onSearchInputBlur","count":4},{"name":"id","count":2},{"name":"dataQa","count":2},{"name":"placeholder","count":2},{"name":"layout","count":2}]